rpi_backlight/__init__.py
rpi_backlight/cli.py
rpi_backlight/gui.py
rpi_backlight/utils.py
rpi_backlight-2.6.0.dist-info/LICENSE
rpi_backlight-2.6.0.dist-info/METADATA
rpi_backlight-2.6.0.dist-info/WHEEL
rpi_backlight-2.6.0.dist-info/entry_points.txt
rpi_backlight-2.6.0.dist-info/top_level.txt
rpi_backlight-2.6.0.dist-info/RECORD
