Metadata-Version: 2.1
Name: rpi-backlight
Version: 2.6.0
Summary: A Python module for controlling power and brightness of the official Raspberry Pi 7" touch display.
Home-page: https://github.com/linusg/rpi-backlight
Download-URL: https://pypi.org/project/rpi-backlight
Author: Linus Groh
Author-email: mail@linusgroh.de
License: MIT
Keywords: raspberry pi,display,touchscreen,brightness,backlight
Classifier: Development Status :: 5 - Production/Stable
Classifier: Environment :: Console
Classifier: Environment :: X11 Applications :: GTK
Classifier: Intended Audience :: Developers
Classifier: License :: OSI Approved :: MIT License
Classifier: Operating System :: POSIX :: Linux
Classifier: Programming Language :: Python
Classifier: Programming Language :: Python :: 3 :: Only
Classifier: Programming Language :: Python :: 3.7
Classifier: Programming Language :: Python :: 3.8
Classifier: Programming Language :: Python :: 3.9
Classifier: Programming Language :: Python :: 3.10
Classifier: Programming Language :: Python :: 3.11
Classifier: Topic :: System
Classifier: Topic :: System :: Hardware
Classifier: Topic :: Multimedia
Classifier: Topic :: Utilities
Classifier: Topic :: Software Development :: Libraries
Classifier: Topic :: Software Development :: Libraries :: Python Modules
License-File: LICENSE
